<?xml version="1.0" encoding="utf-8"?>
<localization>
	<entity id="insert-blog">
		<locale lang="fr">Création du blog {documentlabel}</locale>
	</entity>
	<entity id="log-insert-blog">
		<locale lang="fr">log-insert-blog</locale>
	</entity>
	<entity id="insert-post">
		<locale lang="fr">Création du billet {documentlabel}</locale>
	</entity>
	<entity id="log-insert-post">
		<locale lang="fr">log-insert-post</locale>
	</entity>
	<entity id="insert-category">
		<locale lang="fr">Création de la categorie {documentlabel}</locale>
	</entity>
	<entity id="log-insert-category">
		<locale lang="fr">log-insert-category</locale>
	</entity>
	<entity id="insert-keyword">
		<locale lang="fr">Création du mot-clé {documentlabel}</locale>
	</entity>
	<entity id="log-insert-keyword">
		<locale lang="fr">log-insert-keyword</locale>
	</entity>
	<entity id="update-blog">
		<locale lang="fr">Mise à jour du blog {documentlabel}</locale>
	</entity>
	<entity id="log-update-blog">
		<locale lang="fr">log-update-blog</locale>
	</entity>
	<entity id="update-post">
		<locale lang="fr">Mise à jour billet {documentlabel}</locale>
	</entity>
	<entity id="log-update-post">
		<locale lang="fr">log-update-post</locale>
	</entity>
	<entity id="update-category">
		<locale lang="fr">Mise à jour de la categorie {documentlabel}</locale>
	</entity>
	<entity id="log-update-category">
		<locale lang="fr">log-update-category</locale>
	</entity>
	<entity id="update-keyword">
		<locale lang="fr">Mise à jour du mot-clé {documentlabel}</locale>
	</entity>
	<entity id="log-update-keyword">
		<locale lang="fr">log-update-keyword</locale>
	</entity>
	<entity id="deactivated-post">
		<locale lang="fr">Désactivation du billet {documentlabel}</locale>
	</entity>
	<entity id="log-deactivated-post">
		<locale lang="fr">log-deactivated-post</locale>
	</entity>
	<entity id="reactivate-post">
		<locale lang="fr">Réactivation du billet {documentlabel}</locale>
	</entity>
	<entity id="log-reactivate-post">
		<locale lang="fr">log-reactivate-post</locale>
	</entity>
	<entity id="deactivated-blog">
		<locale lang="fr">deactivated.blog {documentlabel}</locale>
	</entity>
	<entity id="log-deactivated-blog">
		<locale lang="fr">log-deactivated-blog</locale>
	</entity>
	<entity id="reactivate-blog">
		<locale lang="fr">reactivate.blog {documentlabel}</locale>
	</entity>
	<entity id="log-reactivate-blog">
		<locale lang="fr">log-reactivate-blog</locale>
	</entity>
	<entity id="activate-post">
		<locale lang="fr">activate.post {documentlabel}</locale>
	</entity>
	<entity id="log-activate-post">
		<locale lang="fr">log-activate-post</locale>
	</entity>
<entity id="update-rootfolder"><locale lang="fr">update.rootfolder {documentlabel}</locale></entity><entity id="log-update-rootfolder"><locale lang="fr">log-update-rootfolder</locale></entity><entity id="insert-blog"><locale lang="fr">insert.blog {documentlabel}</locale></entity><entity id="log-insert-blog"><locale lang="fr">log-insert-blog</locale></entity><entity id="insert-post"><locale lang="fr">insert.post {documentlabel}</locale></entity><entity id="log-insert-post"><locale lang="fr">log-insert-post</locale></entity><entity id="insert-category"><locale lang="fr">insert.category {documentlabel}</locale></entity><entity id="log-insert-category"><locale lang="fr">log-insert-category</locale></entity><entity id="update-post"><locale lang="fr">update.post {documentlabel}</locale></entity><entity id="log-update-post"><locale lang="fr">log-update-post</locale></entity></localization>
